nodifly/__init__.py
nodifly/__main__.py
nodifly/auth.py
nodifly-1.1.7.dist-info/LICENSE.md
nodifly-1.1.7.dist-info/METADATA
nodifly-1.1.7.dist-info/WHEEL
nodifly-1.1.7.dist-info/entry_points.txt
nodifly-1.1.7.dist-info/top_level.txt
nodifly-1.1.7.dist-info/RECORD
