Metadata-Version: 2.1
Name: nodifly
Version: 1.1.7
Summary: Nodifly - Real Time Notifications
Home-page: https://github.com/stephenjhsu/nodifly
Author: Stephen Hsu
Author-email: nodiflycontact@gmail.com
License: UNKNOWN
Platform: UNKNOWN
Classifier: Programming Language :: Python :: 3
Classifier: License :: OSI Approved :: MIT License
Classifier: Operating System :: OS Independent
